model_dml/__init__.py
model_dml/dml.py
model_dml/py.typed
model_dml-0.1.0.dist-info/METADATA
model_dml-0.1.0.dist-info/WHEEL
model_dml-0.1.0.dist-info/licenses/AUTHORS.rst
model_dml-0.1.0.dist-info/licenses/LICENSE
model_dml-0.1.0.dist-info/RECORD
