Metadata-Version: 2.1
Name: model_dml
Version: 0.1.0
Summary: A package for SQLAlchemy models DML mixins.
Project-URL: Homepage, https://lab.frogg.it/dorianturba/model_dml
Project-URL: Bug Tracker, https://lab.frogg.it/dorianturba/model_dml
Author-email: Dorian Turba <contact.5oldw@8shield.net>
License-File: AUTHORS.rst
License-File: LICENSE
Classifier: Development Status :: 3 - Alpha
Classifier: License :: OSI Approved :: MIT License
Classifier: Operating System :: OS Independent
Classifier: Programming Language :: Python :: 3
Classifier: Programming Language :: Python :: 3.8
Classifier: Programming Language :: Python :: 3.9
Classifier: Programming Language :: Python :: 3.10
Classifier: Programming Language :: Python :: 3.11
Classifier: Typing :: Typed
Requires-Python: <3.12,>=3.8
Requires-Dist: sqlalchemy<3.0,>=1.4
Provides-Extra: all
Requires-Dist: model-dml[quality]; extra == 'all'
Requires-Dist: model-dml[test]; extra == 'all'
Provides-Extra: quality
Requires-Dist: black; extra == 'quality'
Requires-Dist: flake8; extra == 'quality'
Requires-Dist: isort; extra == 'quality'
Requires-Dist: mypy; extra == 'quality'
Requires-Dist: pre-commit; extra == 'quality'
Requires-Dist: ruff; extra == 'quality'
Provides-Extra: test
Requires-Dist: asyncpg<1.0; extra == 'test'
Requires-Dist: coverage; extra == 'test'
Requires-Dist: fake-session-maker>=0.1.0; extra == 'test'
Requires-Dist: psycopg2<3.0; extra == 'test'
Requires-Dist: pydantic-settings; extra == 'test'
Requires-Dist: pydantic[dotenv]; extra == 'test'
Requires-Dist: pytest; extra == 'test'
Requires-Dist: pytest-asyncio; extra == 'test'
